README.md
setup.py
flood_tool/__init__.py
flood_tool/analysis.py
flood_tool/geo.py
flood_tool/live.py
flood_tool/mapping.py
flood_tool/tool.py
msoifloodp.egg-info/PKG-INFO
msoifloodp.egg-info/SOURCES.txt
msoifloodp.egg-info/dependency_links.txt
msoifloodp.egg-info/top_level.txt